{
  "hash": "c31457ad",
  "configHash": "f43abf07",
  "lockfileHash": "f331e9b3",
  "browserHash": "47fd60f0",
  "optimized": {
    "react": {
      "src": "../../node_modules/react/index.js",
      "file": "react.js",
      "fileHash": "57bdd1b6",
      "needsInterop": true
    },
    "react-dom": {
      "src": "../../node_modules/react-dom/index.js",
      "file": "react-dom.js",
      "fileHash": "ba6777d1",
      "needsInterop": true
    },
    "react/jsx-dev-runtime": {
      "src": "../../node_modules/react/jsx-dev-runtime.js",
      "file": "react_jsx-dev-runtime.js",
      "fileHash": "f6d1bc1f",
      "needsInterop": true
    },
    "react/jsx-runtime": {
      "src": "../../node_modules/react/jsx-runtime.js",
      "file": "react_jsx-runtime.js",
      "fileHash": "b99c33bc",
      "needsInterop": true
    },
    "@supabase/supabase-js": {
      "src": "../../node_modules/@supabase/supabase-js/dist/module/index.js",
      "file": "@supabase_supabase-js.js",
      "fileHash": "966cce2f",
      "needsInterop": false
    },
    "react-dom/client": {
      "src": "../../node_modules/react-dom/client.js",
      "file": "react-dom_client.js",
      "fileHash": "ce29d24c",
      "needsInterop": true
    },
    "react-router-dom": {
      "src": "../../node_modules/react-router-dom/dist/index.mjs",
      "file": "react-router-dom.js",
      "fileHash": "bbe42173",
      "needsInterop": false
    }
  },
  "chunks": {
    "chunk-ZZLBGYQN": {
      "file": "chunk-ZZLBGYQN.js"
    },
    "chunk-65KY755N": {
      "file": "chunk-65KY755N.js"
    },
    "browser-VLKRZ7RP": {
      "file": "browser-VLKRZ7RP.js"
    },
    "chunk-C5A7FNJB": {
      "file": "chunk-C5A7FNJB.js"
    },
    "chunk-V4OQ3NZ2": {
      "file": "chunk-V4OQ3NZ2.js"
    }
  }
}